simplelayout/__init__.py
simplelayout/__main__.py
simplelayout/cli/__init__.py
simplelayout/cli/cli_generate.py
simplelayout/generator/__init__.py
simplelayout/generator/core.py
simplelayout/generator/utils.py
simplelayoutfreeneuro-1.1.dist-info/METADATA
simplelayoutfreeneuro-1.1.dist-info/WHEEL
simplelayoutfreeneuro-1.1.dist-info/top_level.txt
simplelayoutfreeneuro-1.1.dist-info/RECORD
